svante-0.4.1.dist-info/METADATA
svante-0.4.1.dist-info/WHEEL
svante-0.4.1.dist-info/entry_points.txt
svante-0.4.1.dist-info/licenses/LICENSE.rst
svante/__init__.py
svante/__main__.py
svante/combine.py
svante/common.py
svante/plot.py
svante/py.typed
svante-0.4.1.dist-info/RECORD
