Metadata-Version: 2.1
Name: svante
Version: 0.4.1
Summary: Configurable Arrhenius plots with uncertainties and ratios
Keywords: science chemistry physical chemistry kinetics rate coefficients temperature dependence
Author-Email: Joel Berendzen <joel@generisbio.com>
License: BSD-3-Clause
Classifier: Development Status :: 5 - Production/Stable
Classifier: Environment :: Console
Classifier: Intended Audience :: Science/Research
Classifier: License :: OSI Approved :: BSD License
Classifier: Natural Language :: English
Classifier: Operating System :: OS Independent
Classifier: Programming Language :: Python :: 3.9
Classifier: Programming Language :: Python :: 3.10
Classifier: Programming Language :: Python :: 3.11
Classifier: Programming Language :: Python :: 3.12
Classifier: Topic :: Scientific/Engineering :: Chemistry
Requires-Python: <3.13,>=3.9
Requires-Dist: attrs>=23.1.0
Requires-Dist: colorama>=0.4.6
Requires-Dist: loguru>=0.7.2
Requires-Dist: matplotlib>=3.8.3
Requires-Dist: numpy>=1.26.4
Requires-Dist: pandas>=2.2.1
Requires-Dist: pint>=0.23
Requires-Dist: pyarrow>=15.0.0
Requires-Dist: pydove>=0.3.5
Requires-Dist: schema>=0.7.5
Requires-Dist: scipy>=1.12.0
Requires-Dist: shellingham>=1.5.4
Requires-Dist: statsdict>=0.1.8
Requires-Dist: tabulate>=0.9.0
Requires-Dist: toml>=0.10.2
Requires-Dist: tqdm>=4.66.2
Requires-Dist: typer>=0.9.0
Requires-Dist: uncertainties>=3.1.7
